LICENSE
MANIFEST.in
README.rst
setup.cfg
setup.py
django_on_demand.egg-info/PKG-INFO
django_on_demand.egg-info/SOURCES.txt
django_on_demand.egg-info/dependency_links.txt
django_on_demand.egg-info/requires.txt
django_on_demand.egg-info/top_level.txt
docs/Makefile
docs/make.bat
docs/build/doctrees/admin.doctree
docs/build/doctrees/endpoints.doctree
docs/build/doctrees/installation.doctree
docs/build/doctrees/models.doctree
docs/build/html/.buildinfo
docs/build/html/admin.html
docs/build/html/endpoints.html
docs/build/html/installation.html
docs/build/html/models.html
docs/build/html/_sources/admin.rst.txt
docs/build/html/_sources/endpoints.rst.txt
docs/build/html/_sources/installation.rst.txt
docs/build/html/_sources/models.rst.txt
docs/source/admin.rst
docs/source/conf.py
docs/source/db-diagram.png
docs/source/endpoints.rst
docs/source/index.rst
docs/source/installation.rst
docs/source/models.rst
docs/source/_build/html/.buildinfo
docs/source/_build/html/admin.html
docs/source/_build/html/endpoints.html
docs/source/_build/html/genindex.html
docs/source/_build/html/index.html
docs/source/_build/html/installation.html
docs/source/_build/html/models.html
docs/source/_build/html/objects.inv
docs/source/_build/html/search.html
docs/source/_build/html/searchindex.js
docs/source/_build/html/.doctrees/admin.doctree
docs/source/_build/html/.doctrees/endpoints.doctree
docs/source/_build/html/.doctrees/environment.pickle
docs/source/_build/html/.doctrees/index.doctree
docs/source/_build/html/.doctrees/installation.doctree
docs/source/_build/html/.doctrees/models.doctree
docs/source/_build/html/_images/db-diagram.png
docs/source/_build/html/_sources/admin.rst.txt
docs/source/_build/html/_sources/endpoints.rst.txt
docs/source/_build/html/_sources/index.rst.txt
docs/source/_build/html/_sources/installation.rst.txt
docs/source/_build/html/_sources/models.rst.txt
docs/source/_build/html/_static/alabaster.css
docs/source/_build/html/_static/basic.css
docs/source/_build/html/_static/custom.css
docs/source/_build/html/_static/doctools.js
docs/source/_build/html/_static/documentation_options.js
docs/source/_build/html/_static/file.png
