Metadata-Version: 1.1
Name: django-on-demand
Version: 2.0.0
Summary: A Django app to manage suppliers and consumers in an on-demand marketplace.
Home-page: https://github.com/piraidev/django-on-demand
Author: Pirai Dev
Author-email: piraidev@gmail.com
License: BSD-3-Clause
Platform: UNKNOWN
Classifier: Environment :: Web Environment
Classifier: Framework :: Django
Classifier: Intended Audience :: Developers
Classifier: License :: OSI Approved :: BSD License
Classifier: Programming Language :: Python :: 3 :: Only
